einindex/__init__.py
einindex/core.py
einindex/grammar.lark
einindex/py.typed
einindex/test_main.py
einindex-0.0.4.dist-info/LICENSE.md
einindex-0.0.4.dist-info/METADATA
einindex-0.0.4.dist-info/WHEEL
einindex-0.0.4.dist-info/top_level.txt
einindex-0.0.4.dist-info/RECORD
